requests_extensions/__init__.py
requests_extensions/hooks.py
requests_extensions/http_adapter.py
requests_extensions/py.typed
requests_extensions/retry.py
requests_extensions/session.py
requests_extensions/settings.py
requests_extensions/utils.py
requests_extensions-1.1.3.dist-info/METADATA
requests_extensions-1.1.3.dist-info/WHEEL
requests_extensions-1.1.3.dist-info/top_level.txt
requests_extensions-1.1.3.dist-info/RECORD
