Metadata-Version: 2.1
Name: requests-extensions
Version: 1.1.3
Summary: DataKitchen Inc. extension of requests package
Author-email: Ricardo Boni <rboni@datakitchen.io>, Brant Watson <bwatson@datakitchen.io>, Diogo Basto <dbasto@datakitchen.io>, Jimmie Högklint <jhogklint@datakitchen.io>, Khanh Tran <ktran@datakitchen.io>, Tyler Stubenvoll <tstubenvoll@datakitchen.io>
License: CLOSED
Project-URL: homepage, https://datakitchen.io
Classifier: Intended Audience :: Developers
Classifier: Operating System :: OS Independent
Classifier: Programming Language :: Python
Classifier: Programming Language :: Python :: 3.10
Requires-Python: >=3.10
Requires-Dist: requests (~=2.31)
Requires-Dist: urllib3 (>=1.26)
Provides-Extra: build
Requires-Dist: setuptools (~=65.3) ; extra == 'build'
Requires-Dist: wheel (~=0.40.0) ; extra == 'build'
Requires-Dist: build (~=0.10.0) ; extra == 'build'
Provides-Extra: dev
Requires-Dist: black[d] (~=23.1.0) ; extra == 'dev'
Requires-Dist: isort (~=5.12.0) ; extra == 'dev'
Requires-Dist: lxml (~=4.9.1) ; extra == 'dev'
Requires-Dist: mypy (~=1.2.0) ; extra == 'dev'
Requires-Dist: pre-commit (~=2.20.0) ; extra == 'dev'
Requires-Dist: types-setuptools (~=65.3) ; extra == 'dev'
Requires-Dist: types-requests (==2.31.0.6) ; extra == 'dev'
Requires-Dist: pytest (~=7.2.0) ; extra == 'dev'
Requires-Dist: pytest-cov (~=4.0.0) ; extra == 'dev'
Requires-Dist: tomli (~=2.0.1) ; extra == 'dev'
Requires-Dist: twine (~=4.0.2) ; extra == 'dev'
